fluids/__init__.py
fluids/atmosphere.py
fluids/compressible.py
fluids/control_valve.py
fluids/core.py
fluids/design_climate.py
fluids/drag.py
fluids/filters.py
fluids/fittings.py
fluids/flow_meter.py
fluids/friction.py
fluids/geometry.py
fluids/jet_pump.py
fluids/mixing.py
fluids/numba.py
fluids/numba_vectorized.py
fluids/open_flow.py
fluids/packed_bed.py
fluids/packed_tower.py
fluids/particle_size_distribution.py
fluids/piping.py
fluids/pump.py
fluids/py.typed
fluids/safety_valve.py
fluids/saltation.py
fluids/separator.py
fluids/two_phase.py
fluids/two_phase_voidage.py
fluids/units.py
fluids/vectorized.py
fluids/constants/__init__.py
fluids/constants/constants.py
fluids/data/3 phase power.csv
fluids/data/ASTM E11 sieves.csv
fluids/data/ISO 3310-1 sieves.csv
fluids/data/Miller 2E 1990 Kb mitre bend.csv
fluids/data/Miller 2E 1990 abrupt contraction K.csv
fluids/data/Miller 2E 1990 conical contractions K part 1.csv
fluids/data/Miller 2E 1990 conical contractions K part 2.csv
fluids/data/Miller 2E 1990 conical diffuser Kd.csv
fluids/data/Miller 2E 1990 entrances rounded beveled K.csv
fluids/data/Miller 2E 1990 smooth bends Kb.csv
fluids/data/Miller 2E 1990 smooth bends Re correction.csv
fluids/data/Miller 2E 1990 smooth bends outlet tangent length correction.csv
fluids/data/residential power.csv
fluids/nrlmsise00/LICENSE
fluids/nrlmsise00/README
fluids/nrlmsise00/__init__.py
fluids/nrlmsise00/nrlmsise_00.py
fluids/nrlmsise00/nrlmsise_00_data.py
fluids/nrlmsise00/nrlmsise_00_header.py
fluids/numerics/__init__.py
fluids/numerics/arrays.py
fluids/numerics/doubledouble.py
fluids/numerics/polynomial_evaluation.py
fluids/numerics/polynomial_roots.py
fluids/numerics/polynomial_utils.py
fluids/numerics/special.py
fluids/optional/__init__.py
fluids/optional/irradiance.py
fluids/optional/pychebfun.py
fluids/optional/spa.py
fluids-1.2.0.dist-info/licenses/AUTHORS
fluids-1.2.0.dist-info/licenses/LICENSE.txt
fluids-1.2.0.dist-info/METADATA
fluids-1.2.0.dist-info/WHEEL
fluids-1.2.0.dist-info/top_level.txt
fluids-1.2.0.dist-info/RECORD
