Metadata-Version: 2.4
Name: fluids
Version: 1.2.0
Summary: Fluid dynamics component of Chemical Engineering Design Library (ChEDL)
Home-page: https://github.com/CalebBell/fluids
Download-URL: https://github.com/CalebBell/fluids/tarball/1.2.0
Author: Caleb Bell
Author-email: Caleb.Andrew.Bell@gmail.com
License: MIT
Keywords: fluid dynamics atmosphere pipe fluids compressible fluid dynamics chemical engineering mechanical engineering valve open channel tank friction pressure drop two phase pump drag reynolds sedimentation engineering pipeline process simulation particle size distribution
Platform: Windows
Platform: Linux
Platform: Mac OS
Platform: Unix
Classifier: Development Status :: 5 - Production/Stable
Classifier: Intended Audience :: Developers
Classifier: Intended Audience :: Education
Classifier: Intended Audience :: Manufacturing
Classifier: Intended Audience :: Science/Research
Classifier: License :: OSI Approved :: MIT License
Classifier: Natural Language :: English
Classifier: Operating System :: MacOS
Classifier: Operating System :: Microsoft :: Windows
Classifier: Operating System :: POSIX
Classifier: Operating System :: POSIX :: BSD
Classifier: Operating System :: POSIX :: Linux
Classifier: Operating System :: Unix
Classifier: Programming Language :: Python
Classifier: Programming Language :: Python :: 3
Classifier: Programming Language :: Python :: 3.8
Classifier: Programming Language :: Python :: 3.9
Classifier: Programming Language :: Python :: 3.10
Classifier: Programming Language :: Python :: 3.11
Classifier: Programming Language :: Python :: 3.12
Classifier: Programming Language :: Python :: 3.13
Classifier: Programming Language :: Python :: 3.14
Classifier: Programming Language :: Python :: Implementation :: CPython
Classifier: Programming Language :: Python :: Implementation :: PyPy
Classifier: Programming Language :: Python :: Implementation :: MicroPython
Classifier: Topic :: Education
Classifier: Topic :: Scientific/Engineering :: Atmospheric Science
Classifier: Topic :: Scientific/Engineering :: Chemistry
Classifier: Topic :: Scientific/Engineering :: Physics
License-File: LICENSE.txt
License-File: AUTHORS
Requires-Dist: numpy>=1.5.0
Requires-Dist: scipy>=1.6.0
Provides-Extra: coverage-documentation
Requires-Dist: coverage>=4.0.3; extra == "coverage-documentation"
Requires-Dist: pint; extra == "coverage-documentation"
Requires-Dist: wsgiref>=0.1.2; extra == "coverage-documentation"
Dynamic: author
Dynamic: author-email
Dynamic: classifier
Dynamic: description
Dynamic: download-url
Dynamic: home-page
Dynamic: keywords
Dynamic: license
Dynamic: license-file
Dynamic: platform
Dynamic: provides-extra
Dynamic: requires-dist
Dynamic: summary
